datasystem/__init__.py
datasystem/cluster_config.json
datasystem/datasystem_worker
datasystem/ds_client.py
datasystem/ds_tensor_client.py
datasystem/hetero_client.py
datasystem/kv_client.py
datasystem/object_client.py
datasystem/sdk_lib_list
datasystem/util.py
datasystem/worker_config.json
datasystem/cli/__init__.py
datasystem/cli/collect_log.py
datasystem/cli/command.py
datasystem/cli/down.py
datasystem/cli/generate_config.py
datasystem/cli/generate_cpp_template.py
datasystem/cli/generate_helm_chart.py
datasystem/cli/runscript.py
datasystem/cli/start.py
datasystem/cli/stop.py
datasystem/cli/up.py
datasystem/cli/common/__init__.py
datasystem/cli/common/constant.py
datasystem/cli/common/parallel.py
datasystem/cli/common/util.py
datasystem/cpp_template/CMakeLists.txt
datasystem/cpp_template/README.md
datasystem/cpp_template/kv_cache_example.cpp
datasystem/cpp_template/run.sh
datasystem/helm_chart/datasystem/Chart.yaml
datasystem/helm_chart/datasystem/values.yaml
datasystem/helm_chart/datasystem/templates/configmap.yaml
datasystem/helm_chart/datasystem/templates/curvezmq_secret.yaml
datasystem/helm_chart/datasystem/templates/etcd_secret.yaml
datasystem/helm_chart/datasystem/templates/namespace.yaml
datasystem/helm_chart/datasystem/templates/priority_class.yaml
datasystem/helm_chart/datasystem/templates/role.yaml
datasystem/helm_chart/datasystem/templates/role_binding.yaml
datasystem/helm_chart/datasystem/templates/service_account.yaml
datasystem/helm_chart/datasystem/templates/worker_deployment.yaml
datasystem/helm_chart/datasystem/templates/sfs-turbo/pv-sfsturbo.yaml
datasystem/helm_chart/datasystem/templates/sfs-turbo/pvc-sfsturbo.yaml
datasystem/include/datasystem/datasystem.h
datasystem/include/datasystem/kv_cache.h
datasystem/include/datasystem/object_cache.h
datasystem/include/datasystem/perf_client.h
datasystem/include/datasystem/context/context.h
datasystem/include/datasystem/hetero_cache/future.h
datasystem/include/datasystem/hetero_cache/hetero_client.h
chariot_ds-0.1.6.dist-info/METADATA
chariot_ds-0.1.6.dist-info/WHEEL
chariot_ds-0.1.6.dist-info/entry_points.txt
chariot_ds-0.1.6.dist-info/top_level.txt
chariot_ds-0.1.6.dist-info/RECORD
