Metadata-Version: 2.4
Name: chariot-ds
Version: 0.1.6
Summary: chariot-ds is a distributed heterogeneous cache system that supports pooled caching across HBM, DDR, and SSD, along with asynchronous, high-efficiency data transmission for NPUs.
Home-page: https://gitee.com/mindspore/chariot-ds
Author: chariot-ds Team
License: Apache 2.0
Keywords: mindspore chariot-ds datasystem
Classifier: Development Status :: 5 - Production/Stable
Classifier: Intended Audience :: Science/Research
Classifier: Intended Audience :: Developers
Classifier: License :: OSI Approved :: Apache Software License
Classifier: Programming Language :: Python :: 3 :: Only
Classifier: Programming Language :: Python :: 3.8
Classifier: Programming Language :: Python :: 3.9
Classifier: Programming Language :: Python :: 3.10
Classifier: Programming Language :: Python :: 3.11
Classifier: Programming Language :: C++
Classifier: Topic :: Scientific/Engineering
Classifier: Topic :: Software Development
Classifier: Topic :: Software Development :: Libraries
Classifier: Topic :: Software Development :: Libraries :: Python Modules
Requires-Python: >=3.8
Dynamic: author
Dynamic: classifier
Dynamic: description
Dynamic: description-content-type
Dynamic: home-page
Dynamic: keywords
Dynamic: license
Dynamic: requires-python
Dynamic: summary
